ioscustomringtones/plist.py
ioscustomringtones-1.0.1.dist-info/METADATA
ioscustomringtones-1.0.1.dist-info/WHEEL
ioscustomringtones-1.0.1.dist-info/entry_points.txt
ioscustomringtones-1.0.1.dist-info/licenses/LICENSE
ioscustomringtones-1.0.1.dist-info/RECORD
