Metadata-Version: 2.1
Name: ioscustomringtones
Version: 1.0.1
Summary: list custom tones in iOS settings by generating `/Media/iTunes_Control/iTunes/Ringtones.plist`
Project-URL: Repository, https://github.com/zacharyburnett/ioscustomringtones
Author-email: Zachary Burnett <zachary.r.burnett@gmail.com>
License: GPLv3
License-File: LICENSE
Keywords: iOS,iPhone,plist,ringtone
Classifier: Development Status :: 4 - Beta
Classifier: Intended Audience :: End Users/Desktop
Classifier: License :: OSI Approved :: GNU General Public License v3 (GPLv3)
Classifier: Programming Language :: Python :: 3
Classifier: Topic :: File Formats
Requires-Python: >=3
Requires-Dist: mutagen
Requires-Dist: typer
